{"nodes": [{"id": "icons_osasaamise_icon", "label": "Communion Icon", "file_type": "image", "source_file": "src/assets/icons/osasaamise.svg", "source_location": null, "source_url": null, "captured_at": null, "author": null, "contributor": null}, {"id": "icons_osasaamise_chalice", "label": "Chalice", "file_type": "image", "source_file": "src/assets/icons/osasaamise.svg", "source_location": "line 5", "source_url": null, "captured_at": null, "author": null, "contributor": null}, {"id": "icons_osasaamise_bread_plate", "label": "Bread/Plate", "file_type": "image", "source_file": "src/assets/icons/osasaamise.svg", "source_location": "line 7-8", "source_url": null, "captured_at": null, "author": null, "contributor": null}, {"id": "icons_osasaamise_cross", "label": "Cross", "file_type": "image", "source_file": "src/assets/icons/osasaamise.svg", "source_location": "line 10-11", "source_url": null, "captured_at": null, "author": null, "contributor": null}, {"id": "icons_osasaamise_concept_communion", "label": "Communion (Lord's Supper)", "file_type": "concept", "source_file": "src/assets/icons/osasaamise.svg", "source_location": null, "source_url": null, "captured_at": null, "author": null, "contributor": null}, {"id": "icons_osasaamise_concept_church_sacrament", "label": "Church Sacrament", "file_type": "concept", "source_file": "src/assets/icons/osasaamise.svg", "source_location": null, "source_url": null, "captured_at": null, "author": null, "contributor": null}], "edges": [], "hyperedges": []}